agently/__init__.py
agently/_version.py
agently/version.py
agently/agents/agent.py
agently/agents/prompts.py
agently/agents/reasoning.py
agently/cli/__init__.py
agently/cli/__main__.py
agently/cli/commands.py
agently/cli/interactive.py
agently/config/__init__.py
agently/config/parser.py
agently/config/schema.json
agently/config/types.py
agently/conversation/context.py
agently/conversation/manager.py
agently/core/__init__.py
agently/errors/__init__.py
agently/errors/handler.py
agently/errors/types.py
agently/models/base.py
agently/models/ollama.py
agently/models/openai.py
agently/plugins/__init__.py
agently/plugins/base.py
agently/plugins/manager.py
agently/plugins/sources.py
agently/utils/README.md
agently/utils/__init__.py
agently/utils/logging.py
agently_cli-0.2.2.dist-info/licenses/LICENSE
agently_cli-0.2.2.dist-info/METADATA
agently_cli-0.2.2.dist-info/WHEEL
agently_cli-0.2.2.dist-info/entry_points.txt
agently_cli-0.2.2.dist-info/top_level.txt
agently_cli-0.2.2.dist-info/RECORD
