Metadata-Version: 2.4
Name: agently-cli
Version: 0.2.2
Summary: Declarative AI Agent Framework
Home-page: https://github.com/onwardplatforms/agently
Author: Onward Platforms
Author-email: info@onwardplatforms.com
License: MIT
Classifier: Development Status :: 4 - Beta
Classifier: Intended Audience :: Developers
Classifier: Programming Language :: Python :: 3
Classifier: Programming Language :: Python :: 3.8
Classifier: Programming Language :: Python :: 3.9
Classifier: Programming Language :: Python :: 3.10
Classifier: Programming Language :: Python :: 3.11
Requires-Python: >=3.8
License-File: LICENSE
Requires-Dist: click
Requires-Dist: semantic-kernel
Requires-Dist: semantic-kernel[mcp]
Requires-Dist: python-dotenv
Requires-Dist: aiohttp
Requires-Dist: jsonschema
Requires-Dist: pyyaml
Requires-Dist: requests
Requires-Dist: typing-extensions
Requires-Dist: agently-sdk
Requires-Dist: azure-identity
Requires-Dist: ollama
Requires-Dist: mcp
Requires-Dist: prompt_toolkit
Provides-Extra: test
Requires-Dist: pytest; extra == "test"
Requires-Dist: pytest-asyncio; extra == "test"
Requires-Dist: pytest-cov; extra == "test"
Requires-Dist: pytest-mock; extra == "test"
Requires-Dist: pytest-timeout; extra == "test"
Provides-Extra: dev
Requires-Dist: black; extra == "dev"
Requires-Dist: flake8; extra == "dev"
Requires-Dist: flake8-docstrings; extra == "dev"
Requires-Dist: isort; extra == "dev"
Requires-Dist: mypy; extra == "dev"
Requires-Dist: pre-commit; extra == "dev"
Requires-Dist: pydantic; extra == "dev"
Requires-Dist: types-requests; extra == "dev"
Requires-Dist: autoflake; extra == "dev"
Requires-Dist: types-jsonschema; extra == "dev"
Requires-Dist: types-PyYAML; extra == "dev"
Dynamic: author
Dynamic: author-email
Dynamic: classifier
Dynamic: description
Dynamic: description-content-type
Dynamic: home-page
Dynamic: license
Dynamic: license-file
Dynamic: provides-extra
Dynamic: requires-dist
Dynamic: requires-python
Dynamic: summary
